PyGAU/__init__.py
PyGAU/benchmark.py
PyGAU/debug.py
pygau-1.3.3.dist-info/licenses/LICENSE
pygau-1.3.3.dist-info/METADATA
pygau-1.3.3.dist-info/WHEEL
pygau-1.3.3.dist-info/top_level.txt
pygau-1.3.3.dist-info/RECORD
