Metadata-Version: 2.4
Name: PyGAU
Version: 1.3.3
Home-page: https://github.com/SpaceProgrammerOriginal/PyGAU
Author: SpaceProgrammer
License: Custom
Classifier: License :: Other/Proprietary License
License-File: LICENSE
Dynamic: author
Dynamic: classifier
Dynamic: description
Dynamic: description-content-type
Dynamic: home-page
Dynamic: license
Dynamic: license-file
